jijmodeling_transpiler_quantum/core/__init__.py
jijmodeling_transpiler_quantum/core/ising_qubo/__init__.py
jijmodeling_transpiler_quantum/core/ising_qubo/ising_qubo.py
jijmodeling_transpiler_quantum/core/qrac/__init__.py
jijmodeling_transpiler_quantum/core/qrac/graph_coloring.py
jijmodeling_transpiler_quantum/qiskit/__init__.py
jijmodeling_transpiler_quantum/qiskit/qaoa/__init__.py
jijmodeling_transpiler_quantum/qiskit/qaoa/ising_hamiltonian.py
jijmodeling_transpiler_quantum/qiskit/qaoa/to_qaoa.py
jijmodeling_transpiler_quantum/qiskit/qrao/__init__.py
jijmodeling_transpiler_quantum/qiskit/qrao/qrao21.py
jijmodeling_transpiler_quantum/qiskit/qrao/qrao31.py
jijmodeling_transpiler_quantum/qiskit/qrao/qrao32.py
jijmodeling_transpiler_quantum/qiskit/qrao/qrao_space_efficient.py
jijmodeling_transpiler_quantum/qiskit/qrao/to_qrac.py
jijmodeling_transpiler_quantum/quri_parts/__init__.py
jijmodeling_transpiler_quantum/quri_parts/qaoa/__init__.py
jijmodeling_transpiler_quantum/quri_parts/qaoa/ising_hamiltonian.py
jijmodeling_transpiler_quantum/quri_parts/qaoa/to_qaoa.py
jijmodeling_transpiler_quantum/quri_parts/qrao/__init__.py
jijmodeling_transpiler_quantum/quri_parts/qrao/qrao21.py
jijmodeling_transpiler_quantum/quri_parts/qrao/qrao31.py
jijmodeling_transpiler_quantum/quri_parts/qrao/to_qrac.py
jijmodeling_transpiler_quantum-0.0.0.dist-info/METADATA
jijmodeling_transpiler_quantum-0.0.0.dist-info/WHEEL
jijmodeling_transpiler_quantum-0.0.0.dist-info/RECORD
