Metadata-Version: 2.1
Name: jijmodeling-transpiler-quantum
Version: 0.0.0
Summary: 
Author: Jij Inc.
Requires-Python: >=3.9.8,<3.11
Classifier: Programming Language :: Python :: 3
Classifier: Programming Language :: Python :: 3.10
Provides-Extra: qiskit
Provides-Extra: quri-parts
Requires-Dist: jijmodeling-transpiler (>=0.6.0rc2,<0.7.0)
Requires-Dist: qiskit[qiskit] (>=0.44.0) ; extra == "qiskit"
Requires-Dist: quri-parts[quri-parts] (>=0.13.0) ; extra == "quri-parts"
